agoralib/__init__.py
agoralib/core.py
agoralib/rules/__init__.py
agoralib/rules/base.py
agoralib/rules/delete.py
agoralib/rules/detection.py
agoralib/rules/info.py
agoralib/rules/merge.py
agoralib/rules/position.py
agoralib/rules/proximity.py
agoralib/rules/shape.py
agoralib/rules/utils.py
agoralib-0.1.2.dist-info/licenses/LICENSE
agoralib-0.1.2.dist-info/METADATA
agoralib-0.1.2.dist-info/WHEEL
agoralib-0.1.2.dist-info/top_level.txt
agoralib-0.1.2.dist-info/RECORD
