Metadata-Version: 2.4
Name: agoralib
Version: 0.1.2
Summary: A lightweight library for bounding box processing, filtering using predefined scenarii.
Author: Jean-Yves Ramel
Author-email: Jean-Yves Ramel <jean-yves.ramel@univ-smb.fr>
License: MIT
Project-URL: Homepage, https://scm.univ-tours.fr/projetspublics/lifat/anr-typoref/libagora.git
Requires-Python: >=3.10
License-File: LICENSE
Requires-Dist: opencv-python>=4.5.0
Requires-Dist: requests
Dynamic: license-file
